{
  "nekonote_button_change": 100,
  "nekonote_button_decide": 100,
  "nekonote_button_detail": 100,
  "nekonote_button_goods": 100,
  "nekonote_button_help": 100,
  "nekonote_button_henkou": 100,
  "nekonote_button_kaijyo": 100,
  "nekonote_button_note": 100,
  "nekonote_button_share": 100,
  "nekonote_button_share_android": 100,
  "nekonote_button_share_ios": 100,
  "nekonote_button_techo": 100,
  "nekonote_button_what": 100,
  "nekonote_course_1": 100,
  "nekonote_course_2": 100,
  "nekonote_course_3": 100,
  "nekonote_course_kanyuchu": 100,
  "nekonote_course_popup": 100,
  "nekonote_text_detail": 100,
  "nekonote_text_food": 100,
  "nekonote_text_nyukai": 100,
  "nekonote_text_select": 100,
  "nekonote_text_settei": 100,
  "nekonote_title": 100,
  "nekonote_title_customize": 100,
  "nekonote_title_okimono": 100,
  "nekonote_title_techo": 100,
  "nekonote_trial": 100,
  "nekonote_window_solo": 100,
  "nekonote_window_solo2": 100
}