<?xml version="1.0" encoding="utf-8"?>
<Animation image="C:\Users\ny\nekoatsume_2\program\Nekoatsume2\Assets\Visual\goods\10hachi_kingyo.png" version="6">
    <Images>
        <Image path="C:\Users\ny\nekoatsume_2\program\Nekoatsume2\Assets\Visual\goods\10hachi_kingyo.png" />
    </Images>
    <Modules>
        <Module h="137" w="146" x="2" y="0" id="0" />
        <Module h="137" w="144" x="148" y="0" id="0" />
        <Module h="137" w="148" x="292" y="0" id="0" />
        <Module h="12" w="9" x="0" y="124" id="0" />
        <Module h="132" w="148" x="0" y="138" id="0" />
        <Module h="133" w="144" x="148" y="138" id="0" />
        <Module h="133" w="145" x="292" y="138" id="0" />
    </Modules>
    <Frames>
        <Frame ab="0" ar="0" at="0" al="0" cb="0" cr="0" ct="0" cl="0" cx="0" cy="0" name="">
            <Sprite m00="1" m01="0" m02="-118" m10="0" m11="1" m12="-92" module_id="0" image_id="0" />
        </Frame>
        <Frame ab="0" ar="0" at="0" al="0" cb="0" cr="0" ct="0" cl="0" cx="0" cy="0" name="">
            <Sprite m00="1" m01="0" m02="-117" m10="0" m11="1" m12="-92" module_id="2" image_id="0" />
        </Frame>
        <Frame ab="0" ar="0" at="0" al="0" cb="0" cr="0" ct="0" cl="0" cx="0" cy="0" name="">
            <Sprite m00="1" m01="0" m02="-117" m10="0" m11="1" m12="-92" module_id="1" image_id="0" />
        </Frame>
        <Frame ab="0" ar="0" at="0" al="0" cb="0" cr="0" ct="0" cl="0" cx="0" cy="0" name="">
            <Sprite m00="1" m01="0" m02="-6" m10="0" m11="1" m12="-3" module_id="3" image_id="0" />
        </Frame>
        <Frame ab="0" ar="0" at="0" al="0" cb="0" cr="0" ct="0" cl="0" cx="0" cy="0" name="">
            <Sprite m00="1" m01="0" m02="-120" m10="0" m11="1" m12="-88" module_id="4" image_id="0" />
        </Frame>
        <Frame ab="0" ar="0" at="0" al="0" cb="0" cr="0" ct="0" cl="0" cx="0" cy="0" name="">
            <Sprite m00="1" m01="0" m02="-117" m10="0" m11="1" m12="-88" module_id="5" image_id="0" />
        </Frame>
        <Frame ab="0" ar="0" at="0" al="0" cb="0" cr="0" ct="0" cl="0" cx="0" cy="0" name="">
            <Sprite m00="1" m01="0" m02="-117" m10="0" m11="1" m12="-88" module_id="6" image_id="0" />
        </Frame>
        <Frame ab="0" ar="0" at="0" al="0" cb="27" cr="25" ct="3" cl="5" cx="0" cy="0" name="xy">
            <Sprite m00="1" m01="0" m02="-118" m10="0" m11="1" m12="-93" module_id="0" image_id="0" />
        </Frame>
    </Frames>
    <Actions>
        <Action name="">
            <MechModel ax="0" ay="0" flag="0" vx="0" vy="0" enable_pre="False" pre="256" />
            <Sequence duration="1" id="0" />
            <Sequence duration="1" id="0" />
            <Sequence duration="1" id="0" />
            <Sequence duration="1" id="0" />
            <Sequence duration="1" id="0" />
            <Sequence duration="1" id="1" />
            <Sequence duration="1" id="1" />
            <Sequence duration="1" id="1" />
            <Sequence duration="1" id="1" />
            <Sequence duration="1" id="1" />
            <Sequence duration="1" id="2" />
            <Sequence duration="1" id="2" />
            <Sequence duration="1" id="2" />
            <Sequence duration="1" id="2" />
            <Sequence duration="1" id="2" />
            <Sequence duration="1" id="1" />
            <Sequence duration="1" id="1" />
            <Sequence duration="1" id="1" />
            <Sequence duration="1" id="1" />
            <Sequence duration="1" id="1" />
        </Action>
        <Action name="">
            <MechModel ax="0" ay="0" flag="0" vx="0" vy="0" enable_pre="False" pre="256" />
            <Sequence duration="1" id="3" />
            <Sequence duration="1" id="3" />
            <Sequence duration="1" id="3" />
        </Action>
        <Action name="">
            <MechModel ax="0" ay="0" flag="0" vx="0" vy="0" enable_pre="False" pre="256" />
            <Sequence duration="1" id="3" />
            <Sequence duration="1" id="3" />
            <Sequence duration="1" id="3" />
        </Action>
        <Action name="">
            <MechModel ax="0" ay="0" flag="0" vx="0" vy="0" enable_pre="False" pre="256" />
            <Sequence duration="1" id="4" />
            <Sequence duration="1" id="4" />
            <Sequence duration="1" id="4" />
            <Sequence duration="1" id="4" />
            <Sequence duration="1" id="4" />
            <Sequence duration="1" id="5" />
            <Sequence duration="1" id="5" />
            <Sequence duration="1" id="5" />
            <Sequence duration="1" id="5" />
            <Sequence duration="1" id="5" />
            <Sequence duration="1" id="6" />
            <Sequence duration="1" id="6" />
            <Sequence duration="1" id="6" />
            <Sequence duration="1" id="6" />
            <Sequence duration="1" id="6" />
            <Sequence duration="1" id="5" />
            <Sequence duration="1" id="5" />
            <Sequence duration="1" id="5" />
            <Sequence duration="1" id="5" />
            <Sequence duration="1" id="5" />
        </Action>
        <Action name="">
            <MechModel ax="0" ay="0" flag="0" vx="0" vy="0" enable_pre="False" pre="256" />
            <Sequence duration="1" id="7" />
        </Action>
    </Actions>
</Animation>